torahbiblecodes/D.py
torahbiblecodes/TBC.py
torahbiblecodes/__init__.py
torahbiblecodes/baphomet.py
torahbiblecodes/query.py
torahbiblecodes/test.py
torahbiblecodes/modules/__init__.py
torahbiblecodes/modules/conversions.py
torahbiblecodes/modules/query.py
torahbiblecodes/resources/data/__init__.py
torahbiblecodes/resources/func/db.py
torahbiblecodes/resources/func/mod_10ListOfIndexesCustomCreate.py
torahbiblecodes/resources/func/mod_11TupleOfWordsAndGematriaValuesCreate.py
torahbiblecodes/resources/func/mod_1GetUserInput1.py
torahbiblecodes/resources/func/mod_2TextFileOpen.py
torahbiblecodes/resources/func/mod_3ATextFilePreprocess.py
torahbiblecodes/resources/func/mod_3BTextFileParse.py
torahbiblecodes/resources/func/mod_4ConvertJSONStringsToDicts.py
torahbiblecodes/resources/func/mod_5GetNumberOfTextChosen.py
torahbiblecodes/resources/func/mod_6ZippedTupleCreate.py
torahbiblecodes/resources/func/mod_7DictionaryOfVersesCreate.py
torahbiblecodes/resources/func/mod_8DataObjectsCreate.py
torahbiblecodes/resources/func/mod_99WriteOutputToCSVFile_WordsAndGematriaValues.py
torahbiblecodes/resources/func/mod_9GetNumberValues.py
torahbiblecodes/resources/func/thread.py
torahbiblecodes/resources/func/torah.py
torahbiblecodes/resources/func/utils.py
torahbiblecodes-1.0.5.dist-info/METADATA
torahbiblecodes-1.0.5.dist-info/WHEEL
torahbiblecodes-1.0.5.dist-info/entry_points.txt
torahbiblecodes-1.0.5.dist-info/top_level.txt
torahbiblecodes-1.0.5.dist-info/RECORD
