Metadata-Version: 2.1
Name: torahbiblecodes
Version: 1.0.5
Summary: Torah Bible Codes , An understandable multilanguaje and multithreading bible codes. Study the Torah as never before.
Home-page: UNKNOWN
Author: torahbiblecodes
Author-email: 
License: UNKNOWN
Project-URL: Source, https://github.com/pedroelbanquero/TorahBibleCodes
Keywords: torahbiblecodes
Platform: UNKNOWN
Classifier: Development Status :: 5 - Production/Stable
Classifier: Intended Audience :: Developers
Classifier: License :: OSI Approved :: MIT License
Classifier: Programming Language :: Python :: 3
Classifier: Programming Language :: Python :: 3.6
Classifier: Programming Language :: Python :: 3.9
Requires-Python: >=3.6.0
Requires-Dist: configparser
Requires-Dist: deep-translator
Requires-Dist: lxml
Requires-Dist: python-hebrew-numbers
Requires-Dist: textblob
